pdf_llm_tools/__init__.py
pdf_llm_tools/llm.py
pdf_llm_tools/main.py
pdf_llm_tools/opts.py
pdf_llm_tools/utils.py
pdf_llm_tools/titler/__init__.py
pdf_llm_tools/titler/main.py
pdf_llm_tools/titler/opts.py
pdf_llm_tools-0.0.4.dist-info/METADATA
pdf_llm_tools-0.0.4.dist-info/WHEEL
pdf_llm_tools-0.0.4.dist-info/entry_points.txt
pdf_llm_tools-0.0.4.dist-info/licenses/LICENSE
pdf_llm_tools-0.0.4.dist-info/RECORD
