Metadata-Version: 2.3
Name: pdf-llm-tools
Version: 0.0.4
Summary: A family of LLM-enhanced PDF utilities
Project-URL: Homepage, https://github.com/jcfk/pdf-llm-tools
Project-URL: Repository, https://github.com/jcfk/pdf-llm-tools
Author-email: Jacob Fong <jacobcfong@gmail.com>
License-File: LICENSE
Keywords: llm,pdf
Classifier: License :: OSI Approved :: MIT License
Classifier: Operating System :: OS Independent
Classifier: Programming Language :: Python :: 3.8
Requires-Python: >=3.8
Requires-Dist: openai
Requires-Dist: pdftotext
